MANIFEST.in
README.txt
setup.cfg
setup.py
Solgema/__init__.py
Solgema.NavigationPortlet.egg-info/PKG-INFO
Solgema.NavigationPortlet.egg-info/SOURCES.txt
Solgema.NavigationPortlet.egg-info/dependency_links.txt
Solgema.NavigationPortlet.egg-info/entry_points.txt
Solgema.NavigationPortlet.egg-info/namespace_packages.txt
Solgema.NavigationPortlet.egg-info/not-zip-safe
Solgema.NavigationPortlet.egg-info/requires.txt
Solgema.NavigationPortlet.egg-info/top_level.txt
Solgema/NavigationPortlet/__init__.py
Solgema/NavigationPortlet/config.py
Solgema/NavigationPortlet/configure.zcml
Solgema/NavigationPortlet/interfaces.py
Solgema/NavigationPortlet/profiles.zcml
Solgema/NavigationPortlet/setuphandlers.py
Solgema/NavigationPortlet/vocabularies.py
Solgema/NavigationPortlet/vocabularies.zcml
Solgema/NavigationPortlet/Extensions/Install.py
Solgema/NavigationPortlet/Extensions/__init__.py
Solgema/NavigationPortlet/locales/Solgema.NavigationPortlet-manual.pot
Solgema/NavigationPortlet/locales/Solgema.NavigationPortlet.pot
Solgema/NavigationPortlet/locales/update.sh
Solgema/NavigationPortlet/locales/en/LC_MESSAGES/Solgema.NavigationPortle.mo
Solgema/NavigationPortlet/locales/en/LC_MESSAGES/Solgema.NavigationPortle.po
Solgema/NavigationPortlet/locales/fr/LC_MESSAGES/Solgema.NavigationPortlet.mo
Solgema/NavigationPortlet/locales/fr/LC_MESSAGES/Solgema.NavigationPortlet.po
Solgema/NavigationPortlet/portlets/__init__.py
Solgema/NavigationPortlet/portlets/configure.zcml
Solgema/NavigationPortlet/portlets/contentnavigation.pt
Solgema/NavigationPortlet/portlets/interfaces.py
Solgema/NavigationPortlet/portlets/navigation.pt
Solgema/NavigationPortlet/portlets/navigation.py
Solgema/NavigationPortlet/portlets/navigation_recurse.pt
Solgema/NavigationPortlet/profiles/default/browserlayer.xml
Solgema/NavigationPortlet/profiles/default/cssregistry.xml
Solgema/NavigationPortlet/profiles/default/jsregistry.xml
Solgema/NavigationPortlet/profiles/default/metadata.xml
Solgema/NavigationPortlet/profiles/default/portlets.xml
Solgema/NavigationPortlet/profiles/default/skins.xml
Solgema/NavigationPortlet/profiles/default/solgemanavigationportlet_install.txt
Solgema/NavigationPortlet/profiles/uninstall/cssregistry.xml
Solgema/NavigationPortlet/profiles/uninstall/import_steps.xml
Solgema/NavigationPortlet/profiles/uninstall/jsregistry.xml
Solgema/NavigationPortlet/profiles/uninstall/metadata.xml
