Metadata-Version: 1.1
Name: Solgema.NavigationPortlet
Version: 1.0
Summary: Solgema
Home-page: http://www.martronic.ch/Solgema/plone_products/solgema_blinks
Author: Martronic SA
Author-email: martronic@martronic.ch
License: GPL
Keywords: Solgema,blinks,backlinks
Platform: UNKNOWN
Classifier: Framework :: Plone
Classifier: Programming Language :: Python
Classifier: Topic :: Software Development :: Libraries :: Python Modules
